einfach/__init__.py
einfach/clip.py
einfach/easy.py
einfach/floatutils.py
einfach/pathdialog.py
einfach/termutils.py
einfach-0.2.2.1.dist-info/METADATA
einfach-0.2.2.1.dist-info/WHEEL
einfach-0.2.2.1.dist-info/top_level.txt
einfach-0.2.2.1.dist-info/RECORD
